db_to_sqlite/__init__.py
db_to_sqlite/cli.py
tests/__init__.py
tests/conftest.py
tests/shared.py
tests/test_db_to_sqlite.py
tests/test_docs.py
tests/test_fixtures.py
tests/test_redact.py
db_to_sqlite-1.5.dist-info/LICENSE
db_to_sqlite-1.5.dist-info/METADATA
db_to_sqlite-1.5.dist-info/WHEEL
db_to_sqlite-1.5.dist-info/entry_points.txt
db_to_sqlite-1.5.dist-info/top_level.txt
db_to_sqlite-1.5.dist-info/RECORD
