Metadata-Version: 2.1
Name: db-to-sqlite
Version: 1.5
Summary: CLI tool for exporting tables or queries from any SQL database to a SQLite file
Home-page: https://datasette.io/tools/db-to-sqlite
Author: Simon Willison
License: Apache License, Version 2.0
Project-URL: Documentation, https://github.com/simonw/db-to-sqlite/blob/main/README.md
Project-URL: Changelog, https://github.com/simonw/db-to-sqlite/releases
Project-URL: Source code, https://github.com/simonw/db-to-sqlite
Project-URL: Issues, https://github.com/simonw/db-to-sqlite/issues
Project-URL: CI, https://travis-ci.com/simonw/db-to-sqlite
Classifier: Intended Audience :: Developers
Classifier: Intended Audience :: Science/Research
Classifier: Intended Audience :: End Users/Desktop
Classifier: Topic :: Database
Classifier: License :: OSI Approved :: Apache Software License
Classifier: Programming Language :: Python :: 3.7
Classifier: Programming Language :: Python :: 3.8
Classifier: Programming Language :: Python :: 3.9
Classifier: Programming Language :: Python :: 3.10
Classifier: Programming Language :: Python :: 3.11
Requires-Python: >=3.7
License-File: LICENSE
Requires-Dist: sqlalchemy
Requires-Dist: sqlite-utils (>=2.9.1)
Requires-Dist: click
Provides-Extra: mysql
Requires-Dist: mysqlclient ; extra == 'mysql'
Provides-Extra: postgresql
Requires-Dist: psycopg2 ; extra == 'postgresql'
Provides-Extra: test
Requires-Dist: pytest ; extra == 'test'
Requires-Dist: pytest-timeout ; extra == 'test'
Provides-Extra: test_mysql
Requires-Dist: pytest ; extra == 'test_mysql'
Requires-Dist: mysqlclient ; extra == 'test_mysql'
Provides-Extra: test_postgresql
Requires-Dist: pytest ; extra == 'test_postgresql'
Requires-Dist: psycopg2 ; extra == 'test_postgresql'
